someapi/__init__.py
someapi/b23/__init__.py
someapi/b23/__init__.pyi
someapi/bilibili/__init__.py
someapi/bilibili/api.py
someapi/bilibili/api.pyi
someapi/bilibili/live.py
someapi/bilibili/member.py
someapi/bilibili/member.pyi
someapi/bilivideo/__init__.py
someapi/bilivideo/upcdnbda2.py
someapi/bilivideo/upcdnbda2.pyi
someapi/custom/__init__.py
someapi/custom/bilibili.py
someapi/custom/bilibili.pyi
someapi/custom/douyin.py
someapi/custom/douyin.pyi
someapi/custom/utils.py
someapi/custom/weibo.py
someapi/douyin/__init__.py
someapi/douyin/__init__.pyi
someapi/douyin/creator.py
someapi/douyin/creator.pyi
someapi/douyin/v.py
someapi/douyin/v.pyi
someapi/weibo/__init__.py
someapi/weibo/__init__.pyi
someapi/weibo/passport.py
someapi/weibo/s.py
setaire_someapi-1.0.0.dist-info/LICENSE
setaire_someapi-1.0.0.dist-info/METADATA
setaire_someapi-1.0.0.dist-info/WHEEL
setaire_someapi-1.0.0.dist-info/top_level.txt
setaire_someapi-1.0.0.dist-info/RECORD
