Metadata-Version: 2.1
Name: setaire-someapi
Version: 1.0.0
Home-page: http://119.29.99.24:9980/setaire/python/someapi
Author: setaire
Author-email: admin@example.com
License: MIT
Platform: any
Classifier: Development Status :: 4 - Beta
Classifier: License :: OSI Approved :: MIT License
Classifier: Operating System :: OS Independent
Classifier: Intended Audience :: Developers
Classifier: Programming Language :: Python :: 3 :: Only
Classifier: Programming Language :: Python :: 3.6
Classifier: Programming Language :: Python :: 3.7
Classifier: Programming Language :: Python :: 3.8
Classifier: Programming Language :: Python :: 3.9
Classifier: Programming Language :: Python :: 3.10
Classifier: Topic :: Software Development :: Libraries :: Python Modules
Requires-Python: >=3.6
License-File: LICENSE
Requires-Dist: setaire-sometools ==1.0.1
Requires-Dist: PyExecJS ==1.5.1
Requires-Dist: retry ==0.9.2
